itkwasm_sub_mesh/__init__.py
itkwasm_sub_mesh/_version.py
itkwasm_sub_mesh/sub_mesh.py
itkwasm_sub_mesh/sub_mesh_async.py
itkwasm_sub_mesh-2.0.0.dist-info/METADATA
itkwasm_sub_mesh-2.0.0.dist-info/WHEEL
itkwasm_sub_mesh-2.0.0.dist-info/RECORD
