Metadata-Version: 2.3
Name: itkwasm-sub-mesh
Version: 2.0.0
Summary: Extract a subset of a mesh given by the cell identifiers.
Project-URL: Home, https://github.com/uncbiag/OAI_analysis_2
Project-URL: Source, https://github.com/uncbiag/OAI_analysis_2
License-Expression: Apache-2.0
Keywords: emscripten,itkwasm,wasi,webassembly
Classifier: Development Status :: 3 - Alpha
Classifier: Environment :: WebAssembly
Classifier: Environment :: WebAssembly :: Emscripten
Classifier: Environment :: WebAssembly :: WASI
Classifier: Intended Audience :: Developers
Classifier: Intended Audience :: Science/Research
Classifier: License :: OSI Approved :: Apache Software License
Classifier: Programming Language :: C++
Classifier: Programming Language :: Python
Classifier: Programming Language :: Python :: 3
Classifier: Programming Language :: Python :: 3.8
Classifier: Programming Language :: Python :: 3.9
Classifier: Programming Language :: Python :: 3.10
Classifier: Programming Language :: Python :: 3.11
Classifier: Programming Language :: Python :: 3.12
Requires-Python: >=3.8
Requires-Dist: itkwasm-sub-mesh-emscripten; sys_platform == 'emscripten'
Requires-Dist: itkwasm-sub-mesh-wasi; sys_platform != 'emscripten'
Requires-Dist: itkwasm>=1.0.b171
